{
  "frames": [
    {
      "file": "frame_000.jpg",
      "time": 0.0,
      "log": "Capturing execution frames: advanced_3d_multiview.json"
    },
    {
      "file": "frame_001.jpg",
      "time": 0.16,
      "log": "Capturing execution frames: advanced_3d_multiview.json\n  Validating workflow...\n  [ComfyUI] === /validate endpoint called ===\n  [ComfyUI] Received JSON with keys: ['prompt']\n  [ComfyUI] Prompt has 8 nodes\n  [ComfyUI]   Node 3: DownloadAndLoadDepthAnythingV3Model\n  [ComfyUI]     Inputs: {\"model\": \"da3_large.safetensors\", \"precision\": \"auto\"}\n  [ComfyUI]   Node 21: LoadImageDataSetFromFolder\n  [ComfyUI]     Inputs: {\"folder\": \"SOH\"}\n  [ComfyUI]   Node 27: PreviewImage\n  [ComfyUI]     Inputs: {\"images\": [\"21\", 0]}\n  [ComfyUI]   Node 38: DA3_MultiViewPointCloud\n  [ComfyUI]     Inputs: {\"extrinsics\": [\"39\", 4], \"intrinsics\": [\"39\", 5], \"confidence_threshold\": 0.3, \"downsample\": 4, \"use_icp\": false, \"allow_around_1\": false, \"filter_outliers\": true, \"outlier_percentage\": 5, \"depths\":\n  [ComfyUI]   Node 39: DepthAnythingV3_MultiView\n  [ComfyUI]     Inputs: {\"normalization_mode\": \"Raw\", \"resize_method\": \"resize\", \"invert_depth\": false, \"keep_model_size\": false, \"da3_model\": [\"3\", 0], \"images\": [\"21\", 0]}\n  [ComfyUI]   Node 44: DA3_SavePointCloud\n  [ComfyUI]     Inputs: {\"filename_prefix\": \"pointcloud\", \"pointcloud\": [\"38\", 0]}\n  [ComfyUI]   Node 45: PreviewAny\n  [ComfyUI]     Inputs: {\"preview\": \"\", \"previewMode\": false, \"source\": [\"44\", 0]}\n  [ComfyUI]   Node 48: DA3_PreviewPointCloud\n  [ComfyUI]     Inputs: {\"file_path\": [\"44\", 0], \"color_mode\": \"RGB\", \"preview\": \"\"}\n  [ComfyUI] Generated prompt_id: 1b2d7b28-ccdc-45d8-8b4f-fb4ff84e51bd\n  [ComfyUI] Calling execution.validate_prompt()...\n  [ComfyUI] Validation result: valid=True\n  [ComfyUI] === Validation PASSED ===\n  Queuing workflow for execution...\n  [ComfyUI] got prompt\n  [ComfyUI] [DepthAnythingV3] INFO: Multi-view input: 1 images, size: 680x1208\n  [ComfyUI] [DepthAnythingV3] INFO: Processing 1 images with multi-view attention\n  [ComfyUI] [DepthAnythingV3] INFO: Model input size (after resize): 686x1204"
    },
    {
      "file": "frame_002.jpg",
      "time": 0.41,
      "log": "Capturing execution frames: advanced_3d_multiview.json\n  Validating workflow...\n  [ComfyUI] === /validate endpoint called ===\n  [ComfyUI] Received JSON with keys: ['prompt']\n  [ComfyUI] Prompt has 8 nodes\n  [ComfyUI]   Node 3: DownloadAndLoadDepthAnythingV3Model\n  [ComfyUI]     Inputs: {\"model\": \"da3_large.safetensors\", \"precision\": \"auto\"}\n  [ComfyUI]   Node 21: LoadImageDataSetFromFolder\n  [ComfyUI]     Inputs: {\"folder\": \"SOH\"}\n  [ComfyUI]   Node 27: PreviewImage\n  [ComfyUI]     Inputs: {\"images\": [\"21\", 0]}\n  [ComfyUI]   Node 38: DA3_MultiViewPointCloud\n  [ComfyUI]     Inputs: {\"extrinsics\": [\"39\", 4], \"intrinsics\": [\"39\", 5], \"confidence_threshold\": 0.3, \"downsample\": 4, \"use_icp\": false, \"allow_around_1\": false, \"filter_outliers\": true, \"outlier_percentage\": 5, \"depths\":\n  [ComfyUI]   Node 39: DepthAnythingV3_MultiView\n  [ComfyUI]     Inputs: {\"normalization_mode\": \"Raw\", \"resize_method\": \"resize\", \"invert_depth\": false, \"keep_model_size\": false, \"da3_model\": [\"3\", 0], \"images\": [\"21\", 0]}\n  [ComfyUI]   Node 44: DA3_SavePointCloud\n  [ComfyUI]     Inputs: {\"filename_prefix\": \"pointcloud\", \"pointcloud\": [\"38\", 0]}\n  [ComfyUI]   Node 45: PreviewAny\n  [ComfyUI]     Inputs: {\"preview\": \"\", \"previewMode\": false, \"source\": [\"44\", 0]}\n  [ComfyUI]   Node 48: DA3_PreviewPointCloud\n  [ComfyUI]     Inputs: {\"file_path\": [\"44\", 0], \"color_mode\": \"RGB\", \"preview\": \"\"}\n  [ComfyUI] Generated prompt_id: 1b2d7b28-ccdc-45d8-8b4f-fb4ff84e51bd\n  [ComfyUI] Calling execution.validate_prompt()...\n  [ComfyUI] Validation result: valid=True\n  [ComfyUI] === Validation PASSED ===\n  Queuing workflow for execution...\n  [ComfyUI] got prompt\n  [ComfyUI] [DepthAnythingV3] INFO: Multi-view input: 1 images, size: 680x1208\n  [ComfyUI] [DepthAnythingV3] INFO: Processing 1 images with multi-view attention\n  [ComfyUI] [DepthAnythingV3] INFO: Model input size (after resize): 686x1204"
    },
    {
      "file": "frame_003.jpg",
      "time": 0.58,
      "log": "Capturing execution frames: advanced_3d_multiview.json\n  Validating workflow...\n  [ComfyUI] === /validate endpoint called ===\n  [ComfyUI] Received JSON with keys: ['prompt']\n  [ComfyUI] Prompt has 8 nodes\n  [ComfyUI]   Node 3: DownloadAndLoadDepthAnythingV3Model\n  [ComfyUI]     Inputs: {\"model\": \"da3_large.safetensors\", \"precision\": \"auto\"}\n  [ComfyUI]   Node 21: LoadImageDataSetFromFolder\n  [ComfyUI]     Inputs: {\"folder\": \"SOH\"}\n  [ComfyUI]   Node 27: PreviewImage\n  [ComfyUI]     Inputs: {\"images\": [\"21\", 0]}\n  [ComfyUI]   Node 38: DA3_MultiViewPointCloud\n  [ComfyUI]     Inputs: {\"extrinsics\": [\"39\", 4], \"intrinsics\": [\"39\", 5], \"confidence_threshold\": 0.3, \"downsample\": 4, \"use_icp\": false, \"allow_around_1\": false, \"filter_outliers\": true, \"outlier_percentage\": 5, \"depths\":\n  [ComfyUI]   Node 39: DepthAnythingV3_MultiView\n  [ComfyUI]     Inputs: {\"normalization_mode\": \"Raw\", \"resize_method\": \"resize\", \"invert_depth\": false, \"keep_model_size\": false, \"da3_model\": [\"3\", 0], \"images\": [\"21\", 0]}\n  [ComfyUI]   Node 44: DA3_SavePointCloud\n  [ComfyUI]     Inputs: {\"filename_prefix\": \"pointcloud\", \"pointcloud\": [\"38\", 0]}\n  [ComfyUI]   Node 45: PreviewAny\n  [ComfyUI]     Inputs: {\"preview\": \"\", \"previewMode\": false, \"source\": [\"44\", 0]}\n  [ComfyUI]   Node 48: DA3_PreviewPointCloud\n  [ComfyUI]     Inputs: {\"file_path\": [\"44\", 0], \"color_mode\": \"RGB\", \"preview\": \"\"}\n  [ComfyUI] Generated prompt_id: 1b2d7b28-ccdc-45d8-8b4f-fb4ff84e51bd\n  [ComfyUI] Calling execution.validate_prompt()...\n  [ComfyUI] Validation result: valid=True\n  [ComfyUI] === Validation PASSED ===\n  Queuing workflow for execution...\n  [ComfyUI] got prompt\n  [ComfyUI] [DepthAnythingV3] INFO: Multi-view input: 1 images, size: 680x1208\n  [ComfyUI] [DepthAnythingV3] INFO: Processing 1 images with multi-view attention\n  [ComfyUI] [DepthAnythingV3] INFO: Model input size (after resize): 686x1204"
    },
    {
      "file": "frame_004.jpg",
      "time": 3.46,
      "log": "Capturing execution frames: advanced_3d_multiview.json\n  Validating workflow...\n  [ComfyUI] === /validate endpoint called ===\n  [ComfyUI] Received JSON with keys: ['prompt']\n  [ComfyUI] Prompt has 8 nodes\n  [ComfyUI]   Node 3: DownloadAndLoadDepthAnythingV3Model\n  [ComfyUI]     Inputs: {\"model\": \"da3_large.safetensors\", \"precision\": \"auto\"}\n  [ComfyUI]   Node 21: LoadImageDataSetFromFolder\n  [ComfyUI]     Inputs: {\"folder\": \"SOH\"}\n  [ComfyUI]   Node 27: PreviewImage\n  [ComfyUI]     Inputs: {\"images\": [\"21\", 0]}\n  [ComfyUI]   Node 38: DA3_MultiViewPointCloud\n  [ComfyUI]     Inputs: {\"extrinsics\": [\"39\", 4], \"intrinsics\": [\"39\", 5], \"confidence_threshold\": 0.3, \"downsample\": 4, \"use_icp\": false, \"allow_around_1\": false, \"filter_outliers\": true, \"outlier_percentage\": 5, \"depths\":\n  [ComfyUI]   Node 39: DepthAnythingV3_MultiView\n  [ComfyUI]     Inputs: {\"normalization_mode\": \"Raw\", \"resize_method\": \"resize\", \"invert_depth\": false, \"keep_model_size\": false, \"da3_model\": [\"3\", 0], \"images\": [\"21\", 0]}\n  [ComfyUI]   Node 44: DA3_SavePointCloud\n  [ComfyUI]     Inputs: {\"filename_prefix\": \"pointcloud\", \"pointcloud\": [\"38\", 0]}\n  [ComfyUI]   Node 45: PreviewAny\n  [ComfyUI]     Inputs: {\"preview\": \"\", \"previewMode\": false, \"source\": [\"44\", 0]}\n  [ComfyUI]   Node 48: DA3_PreviewPointCloud\n  [ComfyUI]     Inputs: {\"file_path\": [\"44\", 0], \"color_mode\": \"RGB\", \"preview\": \"\"}\n  [ComfyUI] Generated prompt_id: 1b2d7b28-ccdc-45d8-8b4f-fb4ff84e51bd\n  [ComfyUI] Calling execution.validate_prompt()...\n  [ComfyUI] Validation result: valid=True\n  [ComfyUI] === Validation PASSED ===\n  Queuing workflow for execution...\n  [ComfyUI] got prompt\n  [ComfyUI] [DepthAnythingV3] INFO: Multi-view input: 1 images, size: 680x1208\n  [ComfyUI] [DepthAnythingV3] INFO: Processing 1 images with multi-view attention\n  [ComfyUI] [DepthAnythingV3] INFO: Model input size (after resize): 686x1204\n  [ComfyUI] [DepthAnythingV3] INFO: Model output intrinsics: shape=torch.Size([1, 1, 3, 3]), values=\n  [ComfyUI] tensor([[1.0947e+03, 0.0000e+00, 6.0200e+02],\n  [ComfyUI]         [0.0000e+00, 1.0701e+03, 3.4300e+02],\n  [ComfyUI]         [0.0000e+00, 0.0000e+00, 1.0000e+00]], device='cuda:0')\n  [ComfyUI] [DepthAnythingV3] INFO: Resizing from 686x1204 to 680x1208, scale: h=0.9913, w=1.0033\n  [ComfyUI] [DepthAnythingV3] INFO: Scaled intrinsics (view 0):\n  [ComfyUI] tensor([[1.0984e+03, 0.0000e+00, 6.0400e+02],\n  [ComfyUI]         [0.0000e+00, 1.0607e+03, 3.4000e+02],\n  [ComfyUI]         [0.0000e+00, 0.0000e+00, 1.0000e+00]])\n  [ComfyUI] [DepthAnythingV3] WARNING: Gaussians data is empty - model may not support gaussian output\n  [ComfyUI] [DepthAnythingV3] INFO: Multi-view input: 1 images, size: 680x1208\n  [ComfyUI] [DepthAnythingV3] INFO: Processing 1 images with multi-view attention\n  [ComfyUI] [DepthAnythingV3] INFO: Model input size (after resize): 686x1204\n  [ComfyUI] [DepthAnythingV3] INFO: Model output intrinsics: shape=torch.Size([1, 1, 3, 3]), values=\n  [ComfyUI] tensor([[1.2176e+03, 0.0000e+00, 6.0200e+02],\n  [ComfyUI]         [0.0000e+00, 1.1940e+03, 3.4300e+02],\n  [ComfyUI]         [0.0000e+00, 0.0000e+00, 1.0000e+00]], device='cuda:0')\n  [ComfyUI] [DepthAnythingV3] INFO: Resizing from 686x1204 to 680x1208, scale: h=0.9913, w=1.0033\n  [ComfyUI] [DepthAnythingV3] INFO: Scaled intrinsics (view 0):\n  [ComfyUI] tensor([[1.2217e+03, 0.0000e+00, 6.0400e+02],\n  [ComfyUI]         [0.0000e+00, 1.1835e+03, 3.4000e+02],\n  [ComfyUI]         [0.0000e+00, 0.0000e+00, 1.0000e+00]])\n  [ComfyUI] [DepthAnythingV3] WARNING: Gaussians data is empty - model may not support gaussian output\n  [ComfyUI] [DepthAnythingV3] INFO: Fusing 1 views into world-space point cloud\n  [ComfyUI] [DepthAnythingV3] INFO:   View 0: 319381 points \u2192 319381 after sky filtering (removed 0)\n  [ComfyUI] [DepthAnythingV3] INFO:   View 0: 319381 points \u2192 19835 after 4x downsampling\n  [ComfyUI] [DepthAnythingV3] INFO:   View 0: Outlier filtering: 19835 \u2192 18843 points (removed 992, 5.0% furthest from center)\n  [ComfyUI] [DepthAnythingV3] INFO:   View 0: Contributing 18843 points to combined cloud"
    },
    {
      "file": "frame_005.jpg",
      "time": 3.68,
      "log": "Capturing execution frames: advanced_3d_multiview.json\n  Validating workflow...\n  [ComfyUI] === /validate endpoint called ===\n  [ComfyUI] Received JSON with keys: ['prompt']\n  [ComfyUI] Prompt has 8 nodes\n  [ComfyUI]   Node 3: DownloadAndLoadDepthAnythingV3Model\n  [ComfyUI]     Inputs: {\"model\": \"da3_large.safetensors\", \"precision\": \"auto\"}\n  [ComfyUI]   Node 21: LoadImageDataSetFromFolder\n  [ComfyUI]     Inputs: {\"folder\": \"SOH\"}\n  [ComfyUI]   Node 27: PreviewImage\n  [ComfyUI]     Inputs: {\"images\": [\"21\", 0]}\n  [ComfyUI]   Node 38: DA3_MultiViewPointCloud\n  [ComfyUI]     Inputs: {\"extrinsics\": [\"39\", 4], \"intrinsics\": [\"39\", 5], \"confidence_threshold\": 0.3, \"downsample\": 4, \"use_icp\": false, \"allow_around_1\": false, \"filter_outliers\": true, \"outlier_percentage\": 5, \"depths\":\n  [ComfyUI]   Node 39: DepthAnythingV3_MultiView\n  [ComfyUI]     Inputs: {\"normalization_mode\": \"Raw\", \"resize_method\": \"resize\", \"invert_depth\": false, \"keep_model_size\": false, \"da3_model\": [\"3\", 0], \"images\": [\"21\", 0]}\n  [ComfyUI]   Node 44: DA3_SavePointCloud\n  [ComfyUI]     Inputs: {\"filename_prefix\": \"pointcloud\", \"pointcloud\": [\"38\", 0]}\n  [ComfyUI]   Node 45: PreviewAny\n  [ComfyUI]     Inputs: {\"preview\": \"\", \"previewMode\": false, \"source\": [\"44\", 0]}\n  [ComfyUI]   Node 48: DA3_PreviewPointCloud\n  [ComfyUI]     Inputs: {\"file_path\": [\"44\", 0], \"color_mode\": \"RGB\", \"preview\": \"\"}\n  [ComfyUI] Generated prompt_id: 1b2d7b28-ccdc-45d8-8b4f-fb4ff84e51bd\n  [ComfyUI] Calling execution.validate_prompt()...\n  [ComfyUI] Validation result: valid=True\n  [ComfyUI] === Validation PASSED ===\n  Queuing workflow for execution...\n  [ComfyUI] got prompt\n  [ComfyUI] [DepthAnythingV3] INFO: Multi-view input: 1 images, size: 680x1208\n  [ComfyUI] [DepthAnythingV3] INFO: Processing 1 images with multi-view attention\n  [ComfyUI] [DepthAnythingV3] INFO: Model input size (after resize): 686x1204\n  [ComfyUI] [DepthAnythingV3] INFO: Model output intrinsics: shape=torch.Size([1, 1, 3, 3]), values=\n  [ComfyUI] tensor([[1.0947e+03, 0.0000e+00, 6.0200e+02],\n  [ComfyUI]         [0.0000e+00, 1.0701e+03, 3.4300e+02],\n  [ComfyUI]         [0.0000e+00, 0.0000e+00, 1.0000e+00]], device='cuda:0')\n  [ComfyUI] [DepthAnythingV3] INFO: Resizing from 686x1204 to 680x1208, scale: h=0.9913, w=1.0033\n  [ComfyUI] [DepthAnythingV3] INFO: Scaled intrinsics (view 0):\n  [ComfyUI] tensor([[1.0984e+03, 0.0000e+00, 6.0400e+02],\n  [ComfyUI]         [0.0000e+00, 1.0607e+03, 3.4000e+02],\n  [ComfyUI]         [0.0000e+00, 0.0000e+00, 1.0000e+00]])\n  [ComfyUI] [DepthAnythingV3] WARNING: Gaussians data is empty - model may not support gaussian output\n  [ComfyUI] [DepthAnythingV3] INFO: Multi-view input: 1 images, size: 680x1208\n  [ComfyUI] [DepthAnythingV3] INFO: Processing 1 images with multi-view attention\n  [ComfyUI] [DepthAnythingV3] INFO: Model input size (after resize): 686x1204\n  [ComfyUI] [DepthAnythingV3] INFO: Model output intrinsics: shape=torch.Size([1, 1, 3, 3]), values=\n  [ComfyUI] tensor([[1.2176e+03, 0.0000e+00, 6.0200e+02],\n  [ComfyUI]         [0.0000e+00, 1.1940e+03, 3.4300e+02],\n  [ComfyUI]         [0.0000e+00, 0.0000e+00, 1.0000e+00]], device='cuda:0')\n  [ComfyUI] [DepthAnythingV3] INFO: Resizing from 686x1204 to 680x1208, scale: h=0.9913, w=1.0033\n  [ComfyUI] [DepthAnythingV3] INFO: Scaled intrinsics (view 0):\n  [ComfyUI] tensor([[1.2217e+03, 0.0000e+00, 6.0400e+02],\n  [ComfyUI]         [0.0000e+00, 1.1835e+03, 3.4000e+02],\n  [ComfyUI]         [0.0000e+00, 0.0000e+00, 1.0000e+00]])\n  [ComfyUI] [DepthAnythingV3] WARNING: Gaussians data is empty - model may not support gaussian output\n  [ComfyUI] [DepthAnythingV3] INFO: Fusing 1 views into world-space point cloud\n  [ComfyUI] [DepthAnythingV3] INFO:   View 0: 319381 points \u2192 319381 after sky filtering (removed 0)\n  [ComfyUI] [DepthAnythingV3] INFO:   View 0: 319381 points \u2192 19835 after 4x downsampling\n  [ComfyUI] [DepthAnythingV3] INFO:   View 0: Outlier filtering: 19835 \u2192 18843 points (removed 992, 5.0% furthest from center)\n  [ComfyUI] [DepthAnythingV3] INFO:   View 0: Contributing 18843 points to combined cloud\n  [ComfyUI] [DepthAnythingV3] INFO: Combined point cloud: 18843 total points (view0=18843)\n  [ComfyUI] [DepthAnythingV3] INFO: Fusing 1 views into world-space point cloud\n  [ComfyUI] [DepthAnythingV3] INFO:   View 0: 345703 points \u2192 345703 after sky filtering (removed 0)\n  [ComfyUI] [DepthAnythingV3] INFO:   View 0: 345703 points \u2192 21509 after 4x downsampling"
    },
    {
      "file": "frame_006.jpg",
      "time": 3.88,
      "log": "Capturing execution frames: advanced_3d_multiview.json\n  Validating workflow...\n  [ComfyUI] === /validate endpoint called ===\n  [ComfyUI] Received JSON with keys: ['prompt']\n  [ComfyUI] Prompt has 8 nodes\n  [ComfyUI]   Node 3: DownloadAndLoadDepthAnythingV3Model\n  [ComfyUI]     Inputs: {\"model\": \"da3_large.safetensors\", \"precision\": \"auto\"}\n  [ComfyUI]   Node 21: LoadImageDataSetFromFolder\n  [ComfyUI]     Inputs: {\"folder\": \"SOH\"}\n  [ComfyUI]   Node 27: PreviewImage\n  [ComfyUI]     Inputs: {\"images\": [\"21\", 0]}\n  [ComfyUI]   Node 38: DA3_MultiViewPointCloud\n  [ComfyUI]     Inputs: {\"extrinsics\": [\"39\", 4], \"intrinsics\": [\"39\", 5], \"confidence_threshold\": 0.3, \"downsample\": 4, \"use_icp\": false, \"allow_around_1\": false, \"filter_outliers\": true, \"outlier_percentage\": 5, \"depths\":\n  [ComfyUI]   Node 39: DepthAnythingV3_MultiView\n  [ComfyUI]     Inputs: {\"normalization_mode\": \"Raw\", \"resize_method\": \"resize\", \"invert_depth\": false, \"keep_model_size\": false, \"da3_model\": [\"3\", 0], \"images\": [\"21\", 0]}\n  [ComfyUI]   Node 44: DA3_SavePointCloud\n  [ComfyUI]     Inputs: {\"filename_prefix\": \"pointcloud\", \"pointcloud\": [\"38\", 0]}\n  [ComfyUI]   Node 45: PreviewAny\n  [ComfyUI]     Inputs: {\"preview\": \"\", \"previewMode\": false, \"source\": [\"44\", 0]}\n  [ComfyUI]   Node 48: DA3_PreviewPointCloud\n  [ComfyUI]     Inputs: {\"file_path\": [\"44\", 0], \"color_mode\": \"RGB\", \"preview\": \"\"}\n  [ComfyUI] Generated prompt_id: 1b2d7b28-ccdc-45d8-8b4f-fb4ff84e51bd\n  [ComfyUI] Calling execution.validate_prompt()...\n  [ComfyUI] Validation result: valid=True\n  [ComfyUI] === Validation PASSED ===\n  Queuing workflow for execution...\n  [ComfyUI] got prompt\n  [ComfyUI] [DepthAnythingV3] INFO: Multi-view input: 1 images, size: 680x1208\n  [ComfyUI] [DepthAnythingV3] INFO: Processing 1 images with multi-view attention\n  [ComfyUI] [DepthAnythingV3] INFO: Model input size (after resize): 686x1204\n  [ComfyUI] [DepthAnythingV3] INFO: Model output intrinsics: shape=torch.Size([1, 1, 3, 3]), values=\n  [ComfyUI] tensor([[1.0947e+03, 0.0000e+00, 6.0200e+02],\n  [ComfyUI]         [0.0000e+00, 1.0701e+03, 3.4300e+02],\n  [ComfyUI]         [0.0000e+00, 0.0000e+00, 1.0000e+00]], device='cuda:0')\n  [ComfyUI] [DepthAnythingV3] INFO: Resizing from 686x1204 to 680x1208, scale: h=0.9913, w=1.0033\n  [ComfyUI] [DepthAnythingV3] INFO: Scaled intrinsics (view 0):\n  [ComfyUI] tensor([[1.0984e+03, 0.0000e+00, 6.0400e+02],\n  [ComfyUI]         [0.0000e+00, 1.0607e+03, 3.4000e+02],\n  [ComfyUI]         [0.0000e+00, 0.0000e+00, 1.0000e+00]])\n  [ComfyUI] [DepthAnythingV3] WARNING: Gaussians data is empty - model may not support gaussian output\n  [ComfyUI] [DepthAnythingV3] INFO: Multi-view input: 1 images, size: 680x1208\n  [ComfyUI] [DepthAnythingV3] INFO: Processing 1 images with multi-view attention\n  [ComfyUI] [DepthAnythingV3] INFO: Model input size (after resize): 686x1204\n  [ComfyUI] [DepthAnythingV3] INFO: Model output intrinsics: shape=torch.Size([1, 1, 3, 3]), values=\n  [ComfyUI] tensor([[1.2176e+03, 0.0000e+00, 6.0200e+02],\n  [ComfyUI]         [0.0000e+00, 1.1940e+03, 3.4300e+02],\n  [ComfyUI]         [0.0000e+00, 0.0000e+00, 1.0000e+00]], device='cuda:0')\n  [ComfyUI] [DepthAnythingV3] INFO: Resizing from 686x1204 to 680x1208, scale: h=0.9913, w=1.0033\n  [ComfyUI] [DepthAnythingV3] INFO: Scaled intrinsics (view 0):\n  [ComfyUI] tensor([[1.2217e+03, 0.0000e+00, 6.0400e+02],\n  [ComfyUI]         [0.0000e+00, 1.1835e+03, 3.4000e+02],\n  [ComfyUI]         [0.0000e+00, 0.0000e+00, 1.0000e+00]])\n  [ComfyUI] [DepthAnythingV3] WARNING: Gaussians data is empty - model may not support gaussian output\n  [ComfyUI] [DepthAnythingV3] INFO: Fusing 1 views into world-space point cloud\n  [ComfyUI] [DepthAnythingV3] INFO:   View 0: 319381 points \u2192 319381 after sky filtering (removed 0)\n  [ComfyUI] [DepthAnythingV3] INFO:   View 0: 319381 points \u2192 19835 after 4x downsampling\n  [ComfyUI] [DepthAnythingV3] INFO:   View 0: Outlier filtering: 19835 \u2192 18843 points (removed 992, 5.0% furthest from center)\n  [ComfyUI] [DepthAnythingV3] INFO:   View 0: Contributing 18843 points to combined cloud\n  [ComfyUI] [DepthAnythingV3] INFO: Combined point cloud: 18843 total points (view0=18843)\n  [ComfyUI] [DepthAnythingV3] INFO: Fusing 1 views into world-space point cloud\n  [ComfyUI] [DepthAnythingV3] INFO:   View 0: 345703 points \u2192 345703 after sky filtering (removed 0)\n  [ComfyUI] [DepthAnythingV3] INFO:   View 0: 345703 points \u2192 21509 after 4x downsampling\n  [ComfyUI] [DepthAnythingV3] INFO:   View 0: Outlier filtering: 21509 \u2192 20433 points (removed 1076, 5.0% furthest from center)\n  [ComfyUI] [DepthAnythingV3] INFO:   View 0: Contributing 20433 points to combined cloud\n  [ComfyUI] [DepthAnythingV3] INFO: Combined point cloud: 20433 total points (view0=20433)"
    },
    {
      "file": "frame_007.jpg",
      "time": 4.04,
      "log": "Capturing execution frames: advanced_3d_multiview.json\n  Validating workflow...\n  [ComfyUI] === /validate endpoint called ===\n  [ComfyUI] Received JSON with keys: ['prompt']\n  [ComfyUI] Prompt has 8 nodes\n  [ComfyUI]   Node 3: DownloadAndLoadDepthAnythingV3Model\n  [ComfyUI]     Inputs: {\"model\": \"da3_large.safetensors\", \"precision\": \"auto\"}\n  [ComfyUI]   Node 21: LoadImageDataSetFromFolder\n  [ComfyUI]     Inputs: {\"folder\": \"SOH\"}\n  [ComfyUI]   Node 27: PreviewImage\n  [ComfyUI]     Inputs: {\"images\": [\"21\", 0]}\n  [ComfyUI]   Node 38: DA3_MultiViewPointCloud\n  [ComfyUI]     Inputs: {\"extrinsics\": [\"39\", 4], \"intrinsics\": [\"39\", 5], \"confidence_threshold\": 0.3, \"downsample\": 4, \"use_icp\": false, \"allow_around_1\": false, \"filter_outliers\": true, \"outlier_percentage\": 5, \"depths\":\n  [ComfyUI]   Node 39: DepthAnythingV3_MultiView\n  [ComfyUI]     Inputs: {\"normalization_mode\": \"Raw\", \"resize_method\": \"resize\", \"invert_depth\": false, \"keep_model_size\": false, \"da3_model\": [\"3\", 0], \"images\": [\"21\", 0]}\n  [ComfyUI]   Node 44: DA3_SavePointCloud\n  [ComfyUI]     Inputs: {\"filename_prefix\": \"pointcloud\", \"pointcloud\": [\"38\", 0]}\n  [ComfyUI]   Node 45: PreviewAny\n  [ComfyUI]     Inputs: {\"preview\": \"\", \"previewMode\": false, \"source\": [\"44\", 0]}\n  [ComfyUI]   Node 48: DA3_PreviewPointCloud\n  [ComfyUI]     Inputs: {\"file_path\": [\"44\", 0], \"color_mode\": \"RGB\", \"preview\": \"\"}\n  [ComfyUI] Generated prompt_id: 1b2d7b28-ccdc-45d8-8b4f-fb4ff84e51bd\n  [ComfyUI] Calling execution.validate_prompt()...\n  [ComfyUI] Validation result: valid=True\n  [ComfyUI] === Validation PASSED ===\n  Queuing workflow for execution...\n  [ComfyUI] got prompt\n  [ComfyUI] [DepthAnythingV3] INFO: Multi-view input: 1 images, size: 680x1208\n  [ComfyUI] [DepthAnythingV3] INFO: Processing 1 images with multi-view attention\n  [ComfyUI] [DepthAnythingV3] INFO: Model input size (after resize): 686x1204\n  [ComfyUI] [DepthAnythingV3] INFO: Model output intrinsics: shape=torch.Size([1, 1, 3, 3]), values=\n  [ComfyUI] tensor([[1.0947e+03, 0.0000e+00, 6.0200e+02],\n  [ComfyUI]         [0.0000e+00, 1.0701e+03, 3.4300e+02],\n  [ComfyUI]         [0.0000e+00, 0.0000e+00, 1.0000e+00]], device='cuda:0')\n  [ComfyUI] [DepthAnythingV3] INFO: Resizing from 686x1204 to 680x1208, scale: h=0.9913, w=1.0033\n  [ComfyUI] [DepthAnythingV3] INFO: Scaled intrinsics (view 0):\n  [ComfyUI] tensor([[1.0984e+03, 0.0000e+00, 6.0400e+02],\n  [ComfyUI]         [0.0000e+00, 1.0607e+03, 3.4000e+02],\n  [ComfyUI]         [0.0000e+00, 0.0000e+00, 1.0000e+00]])\n  [ComfyUI] [DepthAnythingV3] WARNING: Gaussians data is empty - model may not support gaussian output\n  [ComfyUI] [DepthAnythingV3] INFO: Multi-view input: 1 images, size: 680x1208\n  [ComfyUI] [DepthAnythingV3] INFO: Processing 1 images with multi-view attention\n  [ComfyUI] [DepthAnythingV3] INFO: Model input size (after resize): 686x1204\n  [ComfyUI] [DepthAnythingV3] INFO: Model output intrinsics: shape=torch.Size([1, 1, 3, 3]), values=\n  [ComfyUI] tensor([[1.2176e+03, 0.0000e+00, 6.0200e+02],\n  [ComfyUI]         [0.0000e+00, 1.1940e+03, 3.4300e+02],\n  [ComfyUI]         [0.0000e+00, 0.0000e+00, 1.0000e+00]], device='cuda:0')\n  [ComfyUI] [DepthAnythingV3] INFO: Resizing from 686x1204 to 680x1208, scale: h=0.9913, w=1.0033\n  [ComfyUI] [DepthAnythingV3] INFO: Scaled intrinsics (view 0):\n  [ComfyUI] tensor([[1.2217e+03, 0.0000e+00, 6.0400e+02],\n  [ComfyUI]         [0.0000e+00, 1.1835e+03, 3.4000e+02],\n  [ComfyUI]         [0.0000e+00, 0.0000e+00, 1.0000e+00]])\n  [ComfyUI] [DepthAnythingV3] WARNING: Gaussians data is empty - model may not support gaussian output\n  [ComfyUI] [DepthAnythingV3] INFO: Fusing 1 views into world-space point cloud\n  [ComfyUI] [DepthAnythingV3] INFO:   View 0: 319381 points \u2192 319381 after sky filtering (removed 0)\n  [ComfyUI] [DepthAnythingV3] INFO:   View 0: 319381 points \u2192 19835 after 4x downsampling\n  [ComfyUI] [DepthAnythingV3] INFO:   View 0: Outlier filtering: 19835 \u2192 18843 points (removed 992, 5.0% furthest from center)\n  [ComfyUI] [DepthAnythingV3] INFO:   View 0: Contributing 18843 points to combined cloud\n  [ComfyUI] [DepthAnythingV3] INFO: Combined point cloud: 18843 total points (view0=18843)\n  [ComfyUI] [DepthAnythingV3] INFO: Fusing 1 views into world-space point cloud\n  [ComfyUI] [DepthAnythingV3] INFO:   View 0: 345703 points \u2192 345703 after sky filtering (removed 0)\n  [ComfyUI] [DepthAnythingV3] INFO:   View 0: 345703 points \u2192 21509 after 4x downsampling\n  [ComfyUI] [DepthAnythingV3] INFO:   View 0: Outlier filtering: 21509 \u2192 20433 points (removed 1076, 5.0% furthest from center)\n  [ComfyUI] [DepthAnythingV3] INFO:   View 0: Contributing 20433 points to combined cloud\n  [ComfyUI] [DepthAnythingV3] INFO: Combined point cloud: 20433 total points (view0=20433)\n  [ComfyUI] [DepthAnythingV3] INFO: Saved point cloud to: /tmp/comfy-test-hufzjj7k/ComfyUI-DepthAnythingV3/.comfy-test-env/ComfyUI/output/pointcloud_0000.ply"
    },
    {
      "file": "frame_008.jpg",
      "time": 4.25,
      "log": "Capturing execution frames: advanced_3d_multiview.json\n  Validating workflow...\n  [ComfyUI] === /validate endpoint called ===\n  [ComfyUI] Received JSON with keys: ['prompt']\n  [ComfyUI] Prompt has 8 nodes\n  [ComfyUI]   Node 3: DownloadAndLoadDepthAnythingV3Model\n  [ComfyUI]     Inputs: {\"model\": \"da3_large.safetensors\", \"precision\": \"auto\"}\n  [ComfyUI]   Node 21: LoadImageDataSetFromFolder\n  [ComfyUI]     Inputs: {\"folder\": \"SOH\"}\n  [ComfyUI]   Node 27: PreviewImage\n  [ComfyUI]     Inputs: {\"images\": [\"21\", 0]}\n  [ComfyUI]   Node 38: DA3_MultiViewPointCloud\n  [ComfyUI]     Inputs: {\"extrinsics\": [\"39\", 4], \"intrinsics\": [\"39\", 5], \"confidence_threshold\": 0.3, \"downsample\": 4, \"use_icp\": false, \"allow_around_1\": false, \"filter_outliers\": true, \"outlier_percentage\": 5, \"depths\":\n  [ComfyUI]   Node 39: DepthAnythingV3_MultiView\n  [ComfyUI]     Inputs: {\"normalization_mode\": \"Raw\", \"resize_method\": \"resize\", \"invert_depth\": false, \"keep_model_size\": false, \"da3_model\": [\"3\", 0], \"images\": [\"21\", 0]}\n  [ComfyUI]   Node 44: DA3_SavePointCloud\n  [ComfyUI]     Inputs: {\"filename_prefix\": \"pointcloud\", \"pointcloud\": [\"38\", 0]}\n  [ComfyUI]   Node 45: PreviewAny\n  [ComfyUI]     Inputs: {\"preview\": \"\", \"previewMode\": false, \"source\": [\"44\", 0]}\n  [ComfyUI]   Node 48: DA3_PreviewPointCloud\n  [ComfyUI]     Inputs: {\"file_path\": [\"44\", 0], \"color_mode\": \"RGB\", \"preview\": \"\"}\n  [ComfyUI] Generated prompt_id: 1b2d7b28-ccdc-45d8-8b4f-fb4ff84e51bd\n  [ComfyUI] Calling execution.validate_prompt()...\n  [ComfyUI] Validation result: valid=True\n  [ComfyUI] === Validation PASSED ===\n  Queuing workflow for execution...\n  [ComfyUI] got prompt\n  [ComfyUI] [DepthAnythingV3] INFO: Multi-view input: 1 images, size: 680x1208\n  [ComfyUI] [DepthAnythingV3] INFO: Processing 1 images with multi-view attention\n  [ComfyUI] [DepthAnythingV3] INFO: Model input size (after resize): 686x1204\n  [ComfyUI] [DepthAnythingV3] INFO: Model output intrinsics: shape=torch.Size([1, 1, 3, 3]), values=\n  [ComfyUI] tensor([[1.0947e+03, 0.0000e+00, 6.0200e+02],\n  [ComfyUI]         [0.0000e+00, 1.0701e+03, 3.4300e+02],\n  [ComfyUI]         [0.0000e+00, 0.0000e+00, 1.0000e+00]], device='cuda:0')\n  [ComfyUI] [DepthAnythingV3] INFO: Resizing from 686x1204 to 680x1208, scale: h=0.9913, w=1.0033\n  [ComfyUI] [DepthAnythingV3] INFO: Scaled intrinsics (view 0):\n  [ComfyUI] tensor([[1.0984e+03, 0.0000e+00, 6.0400e+02],\n  [ComfyUI]         [0.0000e+00, 1.0607e+03, 3.4000e+02],\n  [ComfyUI]         [0.0000e+00, 0.0000e+00, 1.0000e+00]])\n  [ComfyUI] [DepthAnythingV3] WARNING: Gaussians data is empty - model may not support gaussian output\n  [ComfyUI] [DepthAnythingV3] INFO: Multi-view input: 1 images, size: 680x1208\n  [ComfyUI] [DepthAnythingV3] INFO: Processing 1 images with multi-view attention\n  [ComfyUI] [DepthAnythingV3] INFO: Model input size (after resize): 686x1204\n  [ComfyUI] [DepthAnythingV3] INFO: Model output intrinsics: shape=torch.Size([1, 1, 3, 3]), values=\n  [ComfyUI] tensor([[1.2176e+03, 0.0000e+00, 6.0200e+02],\n  [ComfyUI]         [0.0000e+00, 1.1940e+03, 3.4300e+02],\n  [ComfyUI]         [0.0000e+00, 0.0000e+00, 1.0000e+00]], device='cuda:0')\n  [ComfyUI] [DepthAnythingV3] INFO: Resizing from 686x1204 to 680x1208, scale: h=0.9913, w=1.0033\n  [ComfyUI] [DepthAnythingV3] INFO: Scaled intrinsics (view 0):\n  [ComfyUI] tensor([[1.2217e+03, 0.0000e+00, 6.0400e+02],\n  [ComfyUI]         [0.0000e+00, 1.1835e+03, 3.4000e+02],\n  [ComfyUI]         [0.0000e+00, 0.0000e+00, 1.0000e+00]])\n  [ComfyUI] [DepthAnythingV3] WARNING: Gaussians data is empty - model may not support gaussian output\n  [ComfyUI] [DepthAnythingV3] INFO: Fusing 1 views into world-space point cloud\n  [ComfyUI] [DepthAnythingV3] INFO:   View 0: 319381 points \u2192 319381 after sky filtering (removed 0)\n  [ComfyUI] [DepthAnythingV3] INFO:   View 0: 319381 points \u2192 19835 after 4x downsampling\n  [ComfyUI] [DepthAnythingV3] INFO:   View 0: Outlier filtering: 19835 \u2192 18843 points (removed 992, 5.0% furthest from center)\n  [ComfyUI] [DepthAnythingV3] INFO:   View 0: Contributing 18843 points to combined cloud\n  [ComfyUI] [DepthAnythingV3] INFO: Combined point cloud: 18843 total points (view0=18843)\n  [ComfyUI] [DepthAnythingV3] INFO: Fusing 1 views into world-space point cloud\n  [ComfyUI] [DepthAnythingV3] INFO:   View 0: 345703 points \u2192 345703 after sky filtering (removed 0)\n  [ComfyUI] [DepthAnythingV3] INFO:   View 0: 345703 points \u2192 21509 after 4x downsampling\n  [ComfyUI] [DepthAnythingV3] INFO:   View 0: Outlier filtering: 21509 \u2192 20433 points (removed 1076, 5.0% furthest from center)\n  [ComfyUI] [DepthAnythingV3] INFO:   View 0: Contributing 20433 points to combined cloud\n  [ComfyUI] [DepthAnythingV3] INFO: Combined point cloud: 20433 total points (view0=20433)\n  [ComfyUI] [DepthAnythingV3] INFO: Saved point cloud to: /tmp/comfy-test-hufzjj7k/ComfyUI-DepthAnythingV3/.comfy-test-env/ComfyUI/output/pointcloud_0000.ply\n  [ComfyUI] [DepthAnythingV3] INFO: Saved point cloud to: /tmp/comfy-test-hufzjj7k/ComfyUI-DepthAnythingV3/.comfy-test-env/ComfyUI/output/pointcloud_0000.ply\n  [ComfyUI] Prompt executed in 4.21 seconds"
    },
    {
      "file": "frame_009.jpg",
      "time": 4.85,
      "log": "Capturing execution frames: advanced_3d_multiview.json\n  Validating workflow...\n  [ComfyUI] === /validate endpoint called ===\n  [ComfyUI] Received JSON with keys: ['prompt']\n  [ComfyUI] Prompt has 8 nodes\n  [ComfyUI]   Node 3: DownloadAndLoadDepthAnythingV3Model\n  [ComfyUI]     Inputs: {\"model\": \"da3_large.safetensors\", \"precision\": \"auto\"}\n  [ComfyUI]   Node 21: LoadImageDataSetFromFolder\n  [ComfyUI]     Inputs: {\"folder\": \"SOH\"}\n  [ComfyUI]   Node 27: PreviewImage\n  [ComfyUI]     Inputs: {\"images\": [\"21\", 0]}\n  [ComfyUI]   Node 38: DA3_MultiViewPointCloud\n  [ComfyUI]     Inputs: {\"extrinsics\": [\"39\", 4], \"intrinsics\": [\"39\", 5], \"confidence_threshold\": 0.3, \"downsample\": 4, \"use_icp\": false, \"allow_around_1\": false, \"filter_outliers\": true, \"outlier_percentage\": 5, \"depths\":\n  [ComfyUI]   Node 39: DepthAnythingV3_MultiView\n  [ComfyUI]     Inputs: {\"normalization_mode\": \"Raw\", \"resize_method\": \"resize\", \"invert_depth\": false, \"keep_model_size\": false, \"da3_model\": [\"3\", 0], \"images\": [\"21\", 0]}\n  [ComfyUI]   Node 44: DA3_SavePointCloud\n  [ComfyUI]     Inputs: {\"filename_prefix\": \"pointcloud\", \"pointcloud\": [\"38\", 0]}\n  [ComfyUI]   Node 45: PreviewAny\n  [ComfyUI]     Inputs: {\"preview\": \"\", \"previewMode\": false, \"source\": [\"44\", 0]}\n  [ComfyUI]   Node 48: DA3_PreviewPointCloud\n  [ComfyUI]     Inputs: {\"file_path\": [\"44\", 0], \"color_mode\": \"RGB\", \"preview\": \"\"}\n  [ComfyUI] Generated prompt_id: 1b2d7b28-ccdc-45d8-8b4f-fb4ff84e51bd\n  [ComfyUI] Calling execution.validate_prompt()...\n  [ComfyUI] Validation result: valid=True\n  [ComfyUI] === Validation PASSED ===\n  Queuing workflow for execution...\n  [ComfyUI] got prompt\n  [ComfyUI] [DepthAnythingV3] INFO: Multi-view input: 1 images, size: 680x1208\n  [ComfyUI] [DepthAnythingV3] INFO: Processing 1 images with multi-view attention\n  [ComfyUI] [DepthAnythingV3] INFO: Model input size (after resize): 686x1204\n  [ComfyUI] [DepthAnythingV3] INFO: Model output intrinsics: shape=torch.Size([1, 1, 3, 3]), values=\n  [ComfyUI] tensor([[1.0947e+03, 0.0000e+00, 6.0200e+02],\n  [ComfyUI]         [0.0000e+00, 1.0701e+03, 3.4300e+02],\n  [ComfyUI]         [0.0000e+00, 0.0000e+00, 1.0000e+00]], device='cuda:0')\n  [ComfyUI] [DepthAnythingV3] INFO: Resizing from 686x1204 to 680x1208, scale: h=0.9913, w=1.0033\n  [ComfyUI] [DepthAnythingV3] INFO: Scaled intrinsics (view 0):\n  [ComfyUI] tensor([[1.0984e+03, 0.0000e+00, 6.0400e+02],\n  [ComfyUI]         [0.0000e+00, 1.0607e+03, 3.4000e+02],\n  [ComfyUI]         [0.0000e+00, 0.0000e+00, 1.0000e+00]])\n  [ComfyUI] [DepthAnythingV3] WARNING: Gaussians data is empty - model may not support gaussian output\n  [ComfyUI] [DepthAnythingV3] INFO: Multi-view input: 1 images, size: 680x1208\n  [ComfyUI] [DepthAnythingV3] INFO: Processing 1 images with multi-view attention\n  [ComfyUI] [DepthAnythingV3] INFO: Model input size (after resize): 686x1204\n  [ComfyUI] [DepthAnythingV3] INFO: Model output intrinsics: shape=torch.Size([1, 1, 3, 3]), values=\n  [ComfyUI] tensor([[1.2176e+03, 0.0000e+00, 6.0200e+02],\n  [ComfyUI]         [0.0000e+00, 1.1940e+03, 3.4300e+02],\n  [ComfyUI]         [0.0000e+00, 0.0000e+00, 1.0000e+00]], device='cuda:0')\n  [ComfyUI] [DepthAnythingV3] INFO: Resizing from 686x1204 to 680x1208, scale: h=0.9913, w=1.0033\n  [ComfyUI] [DepthAnythingV3] INFO: Scaled intrinsics (view 0):\n  [ComfyUI] tensor([[1.2217e+03, 0.0000e+00, 6.0400e+02],\n  [ComfyUI]         [0.0000e+00, 1.1835e+03, 3.4000e+02],\n  [ComfyUI]         [0.0000e+00, 0.0000e+00, 1.0000e+00]])\n  [ComfyUI] [DepthAnythingV3] WARNING: Gaussians data is empty - model may not support gaussian output\n  [ComfyUI] [DepthAnythingV3] INFO: Fusing 1 views into world-space point cloud\n  [ComfyUI] [DepthAnythingV3] INFO:   View 0: 319381 points \u2192 319381 after sky filtering (removed 0)\n  [ComfyUI] [DepthAnythingV3] INFO:   View 0: 319381 points \u2192 19835 after 4x downsampling\n  [ComfyUI] [DepthAnythingV3] INFO:   View 0: Outlier filtering: 19835 \u2192 18843 points (removed 992, 5.0% furthest from center)\n  [ComfyUI] [DepthAnythingV3] INFO:   View 0: Contributing 18843 points to combined cloud\n  [ComfyUI] [DepthAnythingV3] INFO: Combined point cloud: 18843 total points (view0=18843)\n  [ComfyUI] [DepthAnythingV3] INFO: Fusing 1 views into world-space point cloud\n  [ComfyUI] [DepthAnythingV3] INFO:   View 0: 345703 points \u2192 345703 after sky filtering (removed 0)\n  [ComfyUI] [DepthAnythingV3] INFO:   View 0: 345703 points \u2192 21509 after 4x downsampling\n  [ComfyUI] [DepthAnythingV3] INFO:   View 0: Outlier filtering: 21509 \u2192 20433 points (removed 1076, 5.0% furthest from center)\n  [ComfyUI] [DepthAnythingV3] INFO:   View 0: Contributing 20433 points to combined cloud\n  [ComfyUI] [DepthAnythingV3] INFO: Combined point cloud: 20433 total points (view0=20433)\n  [ComfyUI] [DepthAnythingV3] INFO: Saved point cloud to: /tmp/comfy-test-hufzjj7k/ComfyUI-DepthAnythingV3/.comfy-test-env/ComfyUI/output/pointcloud_0000.ply\n  [ComfyUI] [DepthAnythingV3] INFO: Saved point cloud to: /tmp/comfy-test-hufzjj7k/ComfyUI-DepthAnythingV3/.comfy-test-env/ComfyUI/output/pointcloud_0000.ply\n  [ComfyUI] Prompt executed in 4.21 seconds"
    },
    {
      "file": "frame_010.jpg",
      "time": 6.01,
      "log": "Capturing execution frames: advanced_3d_multiview.json\n  Validating workflow...\n  [ComfyUI] === /validate endpoint called ===\n  [ComfyUI] Received JSON with keys: ['prompt']\n  [ComfyUI] Prompt has 8 nodes\n  [ComfyUI]   Node 3: DownloadAndLoadDepthAnythingV3Model\n  [ComfyUI]     Inputs: {\"model\": \"da3_large.safetensors\", \"precision\": \"auto\"}\n  [ComfyUI]   Node 21: LoadImageDataSetFromFolder\n  [ComfyUI]     Inputs: {\"folder\": \"SOH\"}\n  [ComfyUI]   Node 27: PreviewImage\n  [ComfyUI]     Inputs: {\"images\": [\"21\", 0]}\n  [ComfyUI]   Node 38: DA3_MultiViewPointCloud\n  [ComfyUI]     Inputs: {\"extrinsics\": [\"39\", 4], \"intrinsics\": [\"39\", 5], \"confidence_threshold\": 0.3, \"downsample\": 4, \"use_icp\": false, \"allow_around_1\": false, \"filter_outliers\": true, \"outlier_percentage\": 5, \"depths\":\n  [ComfyUI]   Node 39: DepthAnythingV3_MultiView\n  [ComfyUI]     Inputs: {\"normalization_mode\": \"Raw\", \"resize_method\": \"resize\", \"invert_depth\": false, \"keep_model_size\": false, \"da3_model\": [\"3\", 0], \"images\": [\"21\", 0]}\n  [ComfyUI]   Node 44: DA3_SavePointCloud\n  [ComfyUI]     Inputs: {\"filename_prefix\": \"pointcloud\", \"pointcloud\": [\"38\", 0]}\n  [ComfyUI]   Node 45: PreviewAny\n  [ComfyUI]     Inputs: {\"preview\": \"\", \"previewMode\": false, \"source\": [\"44\", 0]}\n  [ComfyUI]   Node 48: DA3_PreviewPointCloud\n  [ComfyUI]     Inputs: {\"file_path\": [\"44\", 0], \"color_mode\": \"RGB\", \"preview\": \"\"}\n  [ComfyUI] Generated prompt_id: 1b2d7b28-ccdc-45d8-8b4f-fb4ff84e51bd\n  [ComfyUI] Calling execution.validate_prompt()...\n  [ComfyUI] Validation result: valid=True\n  [ComfyUI] === Validation PASSED ===\n  Queuing workflow for execution...\n  [ComfyUI] got prompt\n  [ComfyUI] [DepthAnythingV3] INFO: Multi-view input: 1 images, size: 680x1208\n  [ComfyUI] [DepthAnythingV3] INFO: Processing 1 images with multi-view attention\n  [ComfyUI] [DepthAnythingV3] INFO: Model input size (after resize): 686x1204\n  [ComfyUI] [DepthAnythingV3] INFO: Model output intrinsics: shape=torch.Size([1, 1, 3, 3]), values=\n  [ComfyUI] tensor([[1.0947e+03, 0.0000e+00, 6.0200e+02],\n  [ComfyUI]         [0.0000e+00, 1.0701e+03, 3.4300e+02],\n  [ComfyUI]         [0.0000e+00, 0.0000e+00, 1.0000e+00]], device='cuda:0')\n  [ComfyUI] [DepthAnythingV3] INFO: Resizing from 686x1204 to 680x1208, scale: h=0.9913, w=1.0033\n  [ComfyUI] [DepthAnythingV3] INFO: Scaled intrinsics (view 0):\n  [ComfyUI] tensor([[1.0984e+03, 0.0000e+00, 6.0400e+02],\n  [ComfyUI]         [0.0000e+00, 1.0607e+03, 3.4000e+02],\n  [ComfyUI]         [0.0000e+00, 0.0000e+00, 1.0000e+00]])\n  [ComfyUI] [DepthAnythingV3] WARNING: Gaussians data is empty - model may not support gaussian output\n  [ComfyUI] [DepthAnythingV3] INFO: Multi-view input: 1 images, size: 680x1208\n  [ComfyUI] [DepthAnythingV3] INFO: Processing 1 images with multi-view attention\n  [ComfyUI] [DepthAnythingV3] INFO: Model input size (after resize): 686x1204\n  [ComfyUI] [DepthAnythingV3] INFO: Model output intrinsics: shape=torch.Size([1, 1, 3, 3]), values=\n  [ComfyUI] tensor([[1.2176e+03, 0.0000e+00, 6.0200e+02],\n  [ComfyUI]         [0.0000e+00, 1.1940e+03, 3.4300e+02],\n  [ComfyUI]         [0.0000e+00, 0.0000e+00, 1.0000e+00]], device='cuda:0')\n  [ComfyUI] [DepthAnythingV3] INFO: Resizing from 686x1204 to 680x1208, scale: h=0.9913, w=1.0033\n  [ComfyUI] [DepthAnythingV3] INFO: Scaled intrinsics (view 0):\n  [ComfyUI] tensor([[1.2217e+03, 0.0000e+00, 6.0400e+02],\n  [ComfyUI]         [0.0000e+00, 1.1835e+03, 3.4000e+02],\n  [ComfyUI]         [0.0000e+00, 0.0000e+00, 1.0000e+00]])\n  [ComfyUI] [DepthAnythingV3] WARNING: Gaussians data is empty - model may not support gaussian output\n  [ComfyUI] [DepthAnythingV3] INFO: Fusing 1 views into world-space point cloud\n  [ComfyUI] [DepthAnythingV3] INFO:   View 0: 319381 points \u2192 319381 after sky filtering (removed 0)\n  [ComfyUI] [DepthAnythingV3] INFO:   View 0: 319381 points \u2192 19835 after 4x downsampling\n  [ComfyUI] [DepthAnythingV3] INFO:   View 0: Outlier filtering: 19835 \u2192 18843 points (removed 992, 5.0% furthest from center)\n  [ComfyUI] [DepthAnythingV3] INFO:   View 0: Contributing 18843 points to combined cloud\n  [ComfyUI] [DepthAnythingV3] INFO: Combined point cloud: 18843 total points (view0=18843)\n  [ComfyUI] [DepthAnythingV3] INFO: Fusing 1 views into world-space point cloud\n  [ComfyUI] [DepthAnythingV3] INFO:   View 0: 345703 points \u2192 345703 after sky filtering (removed 0)\n  [ComfyUI] [DepthAnythingV3] INFO:   View 0: 345703 points \u2192 21509 after 4x downsampling\n  [ComfyUI] [DepthAnythingV3] INFO:   View 0: Outlier filtering: 21509 \u2192 20433 points (removed 1076, 5.0% furthest from center)\n  [ComfyUI] [DepthAnythingV3] INFO:   View 0: Contributing 20433 points to combined cloud\n  [ComfyUI] [DepthAnythingV3] INFO: Combined point cloud: 20433 total points (view0=20433)\n  [ComfyUI] [DepthAnythingV3] INFO: Saved point cloud to: /tmp/comfy-test-hufzjj7k/ComfyUI-DepthAnythingV3/.comfy-test-env/ComfyUI/output/pointcloud_0000.ply\n  [ComfyUI] [DepthAnythingV3] INFO: Saved point cloud to: /tmp/comfy-test-hufzjj7k/ComfyUI-DepthAnythingV3/.comfy-test-env/ComfyUI/output/pointcloud_0000.ply\n  [ComfyUI] Prompt executed in 4.21 seconds"
    },
    {
      "file": "frame_011.jpg",
      "time": 14.42906665802002,
      "log": "Final screenshot"
    }
  ],
  "total_time": 6.13
}